setup.py
bin/duc
src/disktools/__init__.py
src/disktools/disk_usage.py
src/disktools.egg-info/PKG-INFO
src/disktools.egg-info/SOURCES.txt
src/disktools.egg-info/dependency_links.txt
src/disktools.egg-info/requires.txt
src/disktools.egg-info/top_level.txt