Metadata-Version: 1.1
Name: disktools
Version: 0.0.2
Summary: Extensions to basic disk tools like du, df, etc, but written in python
Home-page: https://github.com/ewiger/disktools
Author: Yauhen Yakimovich
Author-email: eugeny.yakimovitch@gmail.com
License: MIT
Download-URL: https://github.com/ewiger/disktools/tarball/master
Platform: UNKNOWN
Classifier: Intended Audience :: Developers
Classifier: Intended Audience :: System Administrators
Classifier: Programming Language :: Python
Classifier: Programming Language :: Python :: 2.7
Classifier: Development Status :: 4 - Beta
Classifier: Operating System :: POSIX :: Linux
